README
setup.py
django_dumpslow/__init__.py
django_dumpslow/middleware.py
django_dumpslow/models.py
django_dumpslow/utils.py
django_dumpslow.egg-info/PKG-INFO
django_dumpslow.egg-info/SOURCES.txt
django_dumpslow.egg-info/dependency_links.txt
django_dumpslow.egg-info/requires.txt
django_dumpslow.egg-info/top_level.txt
django_dumpslow/management/__init__.py
django_dumpslow/management/commands/__init__.py
django_dumpslow/management/commands/dumpslow.py