Metadata-Version: 1.0
Name: django-dumpslow
Version: 3.0.0
Summary: Django application to log and summarize slow requests
Home-page: https://chris-lamb.co.uk/projects/django-dumpslow
Author: Chris Lamb
Author-email: chris@chris-lamb.co.uk
License: BSD
Platform: UNKNOWN
